{
  "cookies": [
    {
      "name": "session-username",
      "value": "standard_user",
      "domain": "www.saucedemo.com",
      "path": "/",
      "expires": 1758013017,
      "httpOnly": false,
      "secure": false,
      "sameSite": "Lax"
    }
  ],
  "origins": [
    {
      "origin": "https://www.saucedemo.com",
      "localStorage": [
        {
          "name": "backtrace-guid",
          "value": "cf95359f-938f-4b7b-b43d-40b9da314b98"
        },
        {
          "name": "backtrace-last-active",
          "value": "1758012416035"
        }
      ]
    }
  ]
}